TKinterModernThemes/ThemeStyles.py
TKinterModernThemes/WidgetFrame.py
TKinterModernThemes/__init__.py
TKinterModernThemes/examples/accentbutton.py
TKinterModernThemes/examples/allwidgets.py
TKinterModernThemes/examples/combinationdemo.py
TKinterModernThemes/examples/examplelauncher.py
TKinterModernThemes/examples/font.py
TKinterModernThemes/examples/layoutdemo.py
TKinterModernThemes/examples/layoutdemooutput.txt
TKinterModernThemes/examples/matplotlibexample.py
TKinterModernThemes/examples/switch.py
TKinterModernThemes/examples/theme_swap.py
TKinterModernThemes/examples/togglebutton.py
TKinterModernThemes/examples/treeview.py
TKinterModernThemes/examples/treeviewdata.json
TKinterModernThemes/images/azuredark.jpg
TKinterModernThemes/images/azurelight.jpg
TKinterModernThemes/images/notheme.jpg
TKinterModernThemes/images/parkdark.jpg
TKinterModernThemes/images/parklight.jpg
TKinterModernThemes/images/sun-valleydark.jpg
TKinterModernThemes/images/sun-valleylight.jpg
TKinterModernThemes/themes/LICENSE.txt
TKinterModernThemes/themes/azure/azure.tcl
TKinterModernThemes/themes/azure/theme/dark.tcl
TKinterModernThemes/themes/azure/theme/light.tcl
TKinterModernThemes/themes/azure/theme/dark/box-accent.png
TKinterModernThemes/themes/azure/theme/dark/box-basic.png
TKinterModernThemes/themes/azure/theme/dark/box-hover.png
TKinterModernThemes/themes/azure/theme/dark/box-invalid.png
TKinterModernThemes/themes/azure/theme/dark/button-hover.png
TKinterModernThemes/themes/azure/theme/dark/card.png
TKinterModernThemes/themes/azure/theme/dark/check-accent.png
TKinterModernThemes/themes/azure/theme/dark/check-basic.png
TKinterModernThemes/themes/azure/theme/dark/check-hover.png
TKinterModernThemes/themes/azure/theme/dark/check-tri-accent.png
TKinterModernThemes/themes/azure/theme/dark/check-tri-basic.png
TKinterModernThemes/themes/azure/theme/dark/check-tri-hover.png
TKinterModernThemes/themes/azure/theme/dark/circle-accent.png
tkintermodernthemes-1.10.5.dist-info/licenses/LICENSE
tkintermodernthemes-1.10.5.dist-info/METADATA
tkintermodernthemes-1.10.5.dist-info/WHEEL
tkintermodernthemes-1.10.5.dist-info/top_level.txt
tkintermodernthemes-1.10.5.dist-info/RECORD
