Metadata-Version: 2.4
Name: TKinterModernThemes
Version: 1.10.5
Summary: A collection of modern themes with code that makes it easy to integrate into a tkinter project.
Home-page: https://github.com/RobertJN64/TKinterModernThemes
Author: Robert Nies
Author-email: robertjnies@gmail.com
License: MIT
Classifier: Programming Language :: Python
Classifier: Programming Language :: Python :: 3
Classifier: Programming Language :: Python :: 3 :: Only
Classifier: Programming Language :: Python :: 3.8
Classifier: Programming Language :: Python :: 3.9
Classifier: Programming Language :: Python :: 3.10
Classifier: Programming Language :: Python :: 3.11
Classifier: Programming Language :: Python :: 3.12
Requires-Python: >=3.10
License-File: LICENSE
Provides-Extra: matplotlib
Requires-Dist: matplotlib; extra == "matplotlib"
Dynamic: license-file
